Stalemate/__init__.py
Stalemate/draw.py
Stalemate-1.0.0.dist-info/LICENSE
Stalemate-1.0.0.dist-info/METADATA
Stalemate-1.0.0.dist-info/WHEEL
Stalemate-1.0.0.dist-info/top_level.txt
Stalemate-1.0.0.dist-info/RECORD
